flightplan/__init__.py
flightplan/cli.py
flightplan/core.py
flightplan/quickstart/__init__.py
flightplan/quickstart/hello.py
flightplan/render/__init__.py
flightplan/render/job.py
flightplan/render/pipeline.py
flightplan/render/task.py
flightplan/render/utils.py
flightplan/render/var.py
flightplan-0.1.2.dist-info/entry_points.txt
flightplan-0.1.2.dist-info/WHEEL
flightplan-0.1.2.dist-info/METADATA
flightplan-0.1.2.dist-info/RECORD
