Metadata-Version: 2.1
Name: flightplan
Version: 0.1.2
Summary: Code based description for Concourse pipelines
Home-page: https://github.com/eruvanos/flightplan
License: MIT
Keywords: concourse,yaml,ci/cd
Author: Maic Siemering
Author-email: maic@siemering.tech
Requires-Python: >=3.8,<4.0
Classifier: Development Status :: 3 - Alpha
Classifier: Intended Audience :: Developers
Classifier: License :: OSI Approved :: MIT License
Classifier: Operating System :: OS Independent
Classifier: Programming Language :: Python
Classifier: Programming Language :: Python :: 3
Classifier: Programming Language :: Python :: 3.7
Classifier: Programming Language :: Python :: 3.8
Classifier: Programming Language :: Python :: 3.9
Classifier: Topic :: Software Development :: Build Tools
Classifier: Topic :: Software Development :: Code Generators
Requires-Dist: pydantic
Requires-Dist: pyyaml
Requires-Dist: typer
Project-URL: Documentation, https://github.com/eruvanos/flightplan
Project-URL: Repository, https://github.com/eruvanos/flightplan
